setup.cfg
setup.py
bin/disrupt
disrupt/__init__.py
disrupt/main.py
disrupt.egg-info/PKG-INFO
disrupt.egg-info/SOURCES.txt
disrupt.egg-info/dependency_links.txt
disrupt.egg-info/top_level.txt