Metadata-Version: 1.0
Name: disrupt
Version: 1.0.1
Summary: A python "tool" for "interacting" with the terminals of "friends" and "colleagues".
Home-page: http://github.com/dellis23/disrupt
Author: Daniel Ellis
Author-email: ellisd23@gmail.com
License: GPLv3
Platform: UNKNOWN
